subpub.py
subpub-0.9.0.dist-info/LICENSE
subpub-0.9.0.dist-info/METADATA
subpub-0.9.0.dist-info/WHEEL
subpub-0.9.0.dist-info/top_level.txt
subpub-0.9.0.dist-info/RECORD
