Metadata-Version: 2.1
Name: subpub
Version: 0.9.0
Summary: Minimalistic, thread-safe, publish-subscribe API for Python
Home-page: https://github.com/Penlect/subpub
Author: Daniel Andersson
Author-email: daniel.4ndersson@gmail.com
License: MIT
Keywords: publish subscribe pubsub subpub mqtt
Platform: UNKNOWN
Classifier: Development Status :: 5 - Production/Stable
Classifier: Environment :: Console
Classifier: Intended Audience :: Developers
Classifier: License :: OSI Approved :: MIT License
Classifier: Natural Language :: English
Classifier: Operating System :: POSIX :: Linux
Classifier: Operating System :: MacOS
Classifier: Operating System :: Microsoft :: Windows :: Windows 10
Classifier: Programming Language :: Python :: 3
Classifier: Programming Language :: Python :: Implementation :: CPython
Requires-Python: >=3.7
